jupyterlab_github_markdown_alerts_extension/__init__.py
jupyterlab_github_markdown_alerts_extension/_version.py
jupyterlab_github_markdown_alerts_extension-1.0.20.data/data/share/jupyter/labextensions/jupyterlab_github_markdown_alerts_extension/package.json
jupyterlab_github_markdown_alerts_extension-1.0.20.data/data/share/jupyter/labextensions/jupyterlab_github_markdown_alerts_extension/schemas/jupyterlab_github_markdown_alerts_extension/package.json.orig
jupyterlab_github_markdown_alerts_extension-1.0.20.data/data/share/jupyter/labextensions/jupyterlab_github_markdown_alerts_extension/schemas/jupyterlab_github_markdown_alerts_extension/plugin.json
jupyterlab_github_markdown_alerts_extension-1.0.20.data/data/share/jupyter/labextensions/jupyterlab_github_markdown_alerts_extension/static/293.6dcb663e8d1a24602088.js
jupyterlab_github_markdown_alerts_extension-1.0.20.data/data/share/jupyter/labextensions/jupyterlab_github_markdown_alerts_extension/static/728.f34fdd26e5e1346494c8.js
jupyterlab_github_markdown_alerts_extension-1.0.20.data/data/share/jupyter/labextensions/jupyterlab_github_markdown_alerts_extension/static/remoteEntry.ac30b9966e8a0ac3b0b8.js
jupyterlab_github_markdown_alerts_extension-1.0.20.data/data/share/jupyter/labextensions/jupyterlab_github_markdown_alerts_extension/static/style.js
jupyterlab_github_markdown_alerts_extension-1.0.20.data/data/share/jupyter/labextensions/jupyterlab_github_markdown_alerts_extension/static/third-party-licenses.json
jupyterlab_github_markdown_alerts_extension-1.0.20.data/data/share/jupyter/labextensions/jupyterlab_github_markdown_alerts_extension/install.json
jupyterlab_github_markdown_alerts_extension-1.0.20.dist-info/METADATA
jupyterlab_github_markdown_alerts_extension-1.0.20.dist-info/WHEEL
jupyterlab_github_markdown_alerts_extension-1.0.20.dist-info/licenses/LICENSE
jupyterlab_github_markdown_alerts_extension-1.0.20.dist-info/RECORD
